fserver/__init__.py
fserver/app.py
fserver/bean.py
fserver/cmd.py
fserver/conf.py
fserver/fserver_app.py
fserver/git.py
fserver/git_app.py
fserver/path_util.py
fserver/permission.py
fserver/util.py
fserver/static/DPlayer.min.css
fserver/static/DPlayer.min.js
fserver/static/dash.all.min.js
fserver/static/flv.min.js
fserver/static/hls.js@latest
fserver/templates/error.html
fserver/templates/list.html
fserver/templates/string.html
fserver/templates/video.html
fserver-0.1.10.dist-info/LICENSE
fserver-0.1.10.dist-info/METADATA
fserver-0.1.10.dist-info/WHEEL
fserver-0.1.10.dist-info/entry_points.txt
fserver-0.1.10.dist-info/top_level.txt
fserver-0.1.10.dist-info/RECORD
