Metadata-Version: 2.1
Name: fserver
Version: 0.1.10
Summary: File Sharing Server implemented with flask and gevent
Home-page: https://github.com/Carrotor116/fserver
Author: Nonu
Author-email: carrotor116@gmail.com
License: MIT
License-File: LICENSE
Requires-Dist: Flask (>=1.1.2)
Requires-Dist: Flask-HTTPAuth (>=4.6.0)
Requires-Dist: gevent (>=20.6.2)
